eer/__init__.py
eer-0.0.2.dist-info/LICENSE
eer-0.0.2.dist-info/METADATA
eer-0.0.2.dist-info/WHEEL
eer-0.0.2.dist-info/top_level.txt
eer-0.0.2.dist-info/RECORD
