Metadata-Version: 2.1
Name: eer
Version: 0.0.2
Summary: Python package to compute the Equal Error Rate, wrapping lrreval
Author-email: David van Leeuwen <david.vanleeuwen@gmail.com>
License: MIT License
Project-URL: Homepage, https://github.com/davidavidav/eer.py
Project-URL: Bug Tracker, https://github.com/davidavdav/eer.py/issues
Classifier: Programming Language :: Python :: 3
Classifier: License :: OSI Approved :: MIT License
Classifier: Operating System :: OS Independent
Requires-Python: >=3.7
License-File: LICENSE
Requires-Dist: numpy
Requires-Dist: llreval
